nanoqm/_data.py
nanoqm/_version.py
nanoqm/compute_integrals.abi3.so
nanoqm/__init__.py
nanoqm/_logger.py
nanoqm/common.py
nanoqm/compute_integrals.pyi
nanoqm/py.typed
nanoqm/_monkey_patch.py
nanoqm/schedule/scheduleCoupling.py
nanoqm/schedule/__init__.py
nanoqm/schedule/scheduleCP2K.py
nanoqm/schedule/components.py
nanoqm/analysis/tools.py
nanoqm/analysis/__init__.py
nanoqm/workflows/workflow_stddft_spectrum.py
nanoqm/workflows/workflow_coupling.py
nanoqm/workflows/tools.py
nanoqm/workflows/input_validation.py
nanoqm/workflows/__init__.py
nanoqm/workflows/orbitals_type.py
nanoqm/workflows/workflow_coop.py
nanoqm/workflows/initialization.py
nanoqm/workflows/templates.py
nanoqm/workflows/schemas.py
nanoqm/workflows/distribute_jobs.py
nanoqm/workflows/workflow_ipr.py
nanoqm/workflows/workflow_single_points.py
nanoqm/workflows/run_workflow.py
nanoqm/.dylibs/libhdf5.310.dylib
nanoqm/.dylibs/libint2.2.dylib
nanoqm/integrals/__init__.py
nanoqm/integrals/nonAdiabaticCoupling.py
nanoqm/integrals/multipole_matrices.py
nanoqm/basis/BASIS_ADMM_MOLOPT
nanoqm/basis/GTH_POTENTIALS
nanoqm/basis/aux_fit.json
nanoqm/basis/BASIS_MOLOPT
nanoqm/basis/BASIS_ADMM
nanoqm/basis/valence_electrons.json
macosx_x86_64/include/boost/outcome/outcome.gdb.py
nano_qmflows-0.14.2.dist-info/RECORD
nano_qmflows-0.14.2.dist-info/WHEEL
nano_qmflows-0.14.2.dist-info/entry_points.txt
nano_qmflows-0.14.2.dist-info/LICENSE_LIBINT2.txt
nano_qmflows-0.14.2.dist-info/LICENSE_LIBHDF5.txt
nano_qmflows-0.14.2.dist-info/top_level.txt
nano_qmflows-0.14.2.dist-info/LICENSE.txt
nano_qmflows-0.14.2.dist-info/METADATA
test/test_files/BASIS_ADMM_MOLOPT
test/test_files/ethylene.xyz
test/test_files/input_test_absorption_spectrum.yml
test/test_files/He.hdf5
test/test_files/GTH_POTENTIALS
test/test_files/legacy.hdf5
test/test_files/test_files.hdf5
test/test_files/test_initialization.yaml
test/test_files/guanine_distribution.yml
test/test_files/file_distribute_cell_parameters.txt
test/test_files/ethylene_couplings.xyz
test/test_files/input_test_distribute_derivative_couplings.yml
test/test_files/file_cell_parameters.txt
test/test_files/BASIS_MOLOPT_UZH
test/test_files/input_test_b3lyp.yml
test/test_files/ethylene.hdf5
test/test_files/F2.xyz
test/test_files/input_couplings_alphas.yml
