Metadata-Version: 2.1
Name: nano-qmflows
Version: 0.14.2
Summary: Derivative coupling calculation
Author-email: Felipe Zapata & Ivan Infante <f.zapata@esciencecenter.nl>
License: Apache-2.0
Project-URL: Homepage, https://github.com/SCM-NV/nano-qmflows
Project-URL: Bug Tracker, https://github.com/SCM-NV/nano-qmflows/issues
Project-URL: Documentation, https://qmflows-namd.readthedocs.io/en/latest/
Keywords: chemistry,Photochemistry,Simulation
Classifier: License :: OSI Approved :: Apache Software License
Classifier: Natural Language :: English
Classifier: Operating System :: MacOS
Classifier: Operating System :: POSIX :: Linux
Classifier: Programming Language :: C++
Classifier: Programming Language :: Python
Classifier: Programming Language :: Python :: 3
Classifier: Programming Language :: Python :: 3 :: Only
Classifier: Programming Language :: Python :: 3.8
Classifier: Programming Language :: Python :: 3.9
Classifier: Programming Language :: Python :: 3.10
Classifier: Programming Language :: Python :: 3.11
Classifier: Programming Language :: Python :: 3.12
Classifier: Programming Language :: Python :: Implementation :: CPython
Classifier: Development Status :: 4 - Beta
Classifier: Intended Audience :: Science/Research
Classifier: Topic :: Scientific/Engineering :: Chemistry
Classifier: Typing :: Typed
Requires-Python: >=3.8
License-File: LICENSE.txt
License-File: LICENSE_LIBHDF5.txt
License-File: LICENSE_LIBINT2.txt
Requires-Dist: h5py >=2.9.0
Requires-Dist: mendeleev >=0.1.0
Requires-Dist: more-itertools >=2.4.0
Requires-Dist: noodles >=0.3.4
Requires-Dist: numpy <2,>=1.17.3
Requires-Dist: scipy >=1.3.2
Requires-Dist: schema !=0.7.5,>=0.6.0
Requires-Dist: pyyaml >=5.1
Requires-Dist: plams ==1.5.1
Requires-Dist: qmflows >=0.12.1
Requires-Dist: packaging >=17.1
Requires-Dist: Nano-Utils >=2.0.0
Provides-Extra: doc
Requires-Dist: sphinx >=2.1 ; extra == 'doc'
Requires-Dist: sphinx-rtd-theme ; extra == 'doc'
Provides-Extra: lint
Requires-Dist: pydocstyle[toml] >=6.1 ; extra == 'lint'
Requires-Dist: flake8 >=5 ; extra == 'lint'
Requires-Dist: Flake8-pyproject >=1.0.1 ; extra == 'lint'
Requires-Dist: mypy ; extra == 'lint'
Requires-Dist: qmflows ; extra == 'lint'
Requires-Dist: numpy >=1.21 ; extra == 'lint'
Requires-Dist: types-pyyaml ; extra == 'lint'
Requires-Dist: types-setuptools ; extra == 'lint'
Requires-Dist: pyparsing >=3.0.8 ; extra == 'lint'
Requires-Dist: Nano-Utils >=2.0.0 ; extra == 'lint'
Requires-Dist: Nano-CAT ; extra == 'lint'
Provides-Extra: test
Requires-Dist: assertionlib >=2.2.3 ; extra == 'test'
Requires-Dist: pytest >=5.4.0 ; extra == 'test'
Requires-Dist: pytest-cov >=2.3.1 ; extra == 'test'
Requires-Dist: pytest-mock >=0.4.0 ; extra == 'test'
Requires-Dist: ipython >=5.0.0 ; extra == 'test'
